replyowl/__init__.py
replyowl/__version__.py
replyowl/py.typed
replyowl/replyowl.py
replyowl-0.1.19.dist-info/LICENSE
replyowl-0.1.19.dist-info/METADATA
replyowl-0.1.19.dist-info/WHEEL
replyowl-0.1.19.dist-info/RECORD
