Metadata-Version: 2.3
Name: replyowl
Version: 0.1.19
Summary: Email reply body generator for HTML and text
License: GPL-3.0-or-later
Author: Stephen Kent
Author-email: smkent@smkent.net
Requires-Python: >=3.9
Classifier: Development Status :: 3 - Alpha
Classifier: Operating System :: OS Independent
Classifier: Topic :: Communications :: Email
Classifier: Topic :: Software Development :: Libraries :: Python Modules
Classifier: Topic :: Text Processing :: Markup :: HTML
Classifier: Typing :: Typed
Requires-Dist: beautifulsoup4
Requires-Dist: html2text
